Workbook

Sheet SWOT Inputs
B2: INTERNAL FACTOR ANALYSIS SUMMARY (IFAS)
B3: Internal Factors | C3: Rating | D3: Utilization | E3: Comments
B4: Strengths
B5: Commitment to Quality | C5: Strength | D5: Always/Almost Always | E5: It's a strenght but still need to polish it
B6: Geography | C6: Significant Strength | D6: Often | E6: Centrally located, near to several major cities.
B7: Knowledge Base | C7: Strength | D7: Sometimes | E7: Slightly on the strenght side, few new employees that lack of experience.
B8: Support/Recources | C8: Strength | D8: Often | E8: Lots of resources from the main FBO's and the SAT network
B9: Culture of Inclusion and Retention | C9: Strength | D9: Always/Almost Always | E9: Strong emphasis on a family-oriented work environment that fosters personal connection, growth, and well-being.
C10: Strength | D10: Always/Almost Always
B11: Weaknesses
B12: Lack of Experience | C12: Weakness | D12: Sometimes | E12: Few new techs
B13: Aging Workforce | C13: Weakness | D13: Occasionally | E13: Few older techs
B14: Downtime Management | C14: Weakness | D14: Sometimes | E14: While performance improvement is a priority, current processes may still present inefficiencies
C15: Weakness | D15: Sometimes
C16: Weakness | D16: Often
B19: EXTERNAL FACTOR ANALYSIS SUMMARY (EFAS)
B20: External Factors | C20: Likelihood | D20: Impact | E20: Comments
B21: Opportunities
B22: Customer Interactions | C22: Possible | D22: Moderate | E22: Good reputation and support from the local RM
B23: Mandates, obsolescence and targeted STC opportunities. | C23: Very Likely | D23: Major | E23: Good connectivity opportunities in the near future
B24: Develop specific sales Strategies | C24: Very Likely | D24: Major | E24: Addition of Mark Winter to the sales team
B25: FDR, CVR, safety systems. | C25: Possible | D25: Minor | E25: Some interest in the Mexican market. We are AFAC.
B26: Airframe support/maintenance partners | C26: Possible | D26: Moderate | E26: Partnered with Straight flight already.
B27: Customers installing Garmin CJ Suites at lower prices. | C27: Very Likely | D27: Major | E27: Customers complain of our higher quotes.
B28: Threats
B29: Lease Agreements | C29: Unlikely | D29: Major | E29: Good relationship with our new landlord
B30: Vendor Support | C30: Very Likely | D30: Major | E30: Good relationship with most mayor manufacturers
B31: Political Enviroment | C31: Very Likely | D31: Major | E31: New government changes
B32: Mobile competition and the changing market. | C32: Possible | D32: Minor | E32: Not many mobile trucks in the area
B33: Competition | C33: Possible | D33: Moderate | E33: Westart ramping up operations at APA

Sheet SWOT Matrix
A2: Satellite SWOT Matrix
C3: Strengths | E3: Weaknesses
C4: 1. | D4: =IF('SWOT Inputs'!B5=0,"",'SWOT Inputs'!B5) -> Commitment to Quality | E4: 1. | F4: =IF('SWOT Inputs'!B12=0,"",'SWOT Inputs'!B12) -> Lack of Experience
C5: 2. | D5: =IF('SWOT Inputs'!B6=0,"",'SWOT Inputs'!B6) -> Geography | E5: 2. | F5: =IF('SWOT Inputs'!B13=0,"",'SWOT Inputs'!B13) -> Aging Workforce
C6: 3. | D6: =IF('SWOT Inputs'!B7=0,"",'SWOT Inputs'!B7) -> Knowledge Base | E6: 3. | F6: =IF('SWOT Inputs'!B14=0,"",'SWOT Inputs'!B14) -> Downtime Management
C7: 4. | D7: =IF('SWOT Inputs'!B8=0,"",'SWOT Inputs'!B8) -> Support/Recources | E7: 4. | F7: =IF('SWOT Inputs'!B15=0,"",'SWOT Inputs'!B15)
C8: 5. | D8: =IF('SWOT Inputs'!B9=0,"",'SWOT Inputs'!B9) -> Culture of Inclusion and Retention | E8: 5. | F8: =IF('SWOT Inputs'!B16=0,"",'SWOT Inputs'!B16)
A9: Opportunities | C9: SO Strategies | E9: WO Strategies
A10: 1. | B10: =IF('SWOT Inputs'!B22=0,"",'SWOT Inputs'!B22) -> Customer Interactions | C10: 1. | D10: Visit customers while the Regional Manager is in town. | E10: 1. | F10: Offer mentorship programs pairing less experienced employees with senior staff to transfer knowledge and enhance technical capabilities.
A11: 2. | B11: =IF('SWOT Inputs'!B23=0,"",'SWOT Inputs'!B23) -> Mandates, obsolescence and targeted STC opportunities. | C11: 2. | D11: Utilize the existing employee training programs focused on customer empathy and personalization to enhance service quality. | E11: 2. | F11: Enhance employer branding to attract talent passionate about customer-focused innovation
A12: 3. | B12: =IF('SWOT Inputs'!B24=0,"",'SWOT Inputs'!B24) -> Develop specific sales Strategies | C12: 3. | D12: Focus on creating intentional, personalized experiences to instill confidence and care for customers, peers, and partners. | E12: 3. | F12: Encourage knowledge sharing across departments to improve creativity and align company-wide efforts with growth opportunities.
A13: 4. | B13: =IF('SWOT Inputs'!B25=0,"",'SWOT Inputs'!B25) -> FDR, CVR, safety systems. | C13: 4. | D13: Advertise and market for Mexican aircraft and input into the Mexican authorized repair stations like APA | E13: 4. | F13: Address internal silos or inefficiencies by creating cross-functional teams to work on more efficient projects
A14: 5. | B14: =IF('SWOT Inputs'!B26=0,"",'SWOT Inputs'!B26) -> Airframe support/maintenance partners | C14: 5. | D14: With the help of Mark Winter and Marketing, Launch targeted marketing campaigns emphasizing the company’s ability to provide personalized, high-quality services. | E14: 5. | F14: Evaluate the geographical market area for competitive pay scale
A15: Threats | C15: ST Strategies | E15: WT Strategies
A16: 1. | B16: =IF('SWOT Inputs'!B29=0,"",'SWOT Inputs'!B29) -> Lease Agreements | C16: 1. | D16: In regards the CJ project, monitor competitor trends and incorporate insights into innovation strategies to maintain a competitive edge. | E16: 1. | F16: Introduce succession planning and leadership development initiatives to maintain continuity.
A17: 2. | B17: =IF('SWOT Inputs'!B30=0,"",'SWOT Inputs'!B30) -> Vendor Support | C17: 2. | D17: Leverage vendor relationships to improve support deficiencies | E17: 2. | F17: Obtain vendor or career focused training opportunities
A18: 3. | B18: =IF('SWOT Inputs'!B31=0,"",'SWOT Inputs'!B31) -> Political Enviroment | C18: 3. | D18: Use quality as a differentiator to build customer trust. | E18: 3. | F18: Regularly assess team capabilities and implement training programs to prepare for emerging new technologies like Starlink and Gallileo.
A19: 4. | B19: =IF('SWOT Inputs'!B32=0,"",'SWOT Inputs'!B32) -> Mobile competition and the changing market. | C19: 4. | D19: Provide a realistic and obtainable response time | E19: 4. | F19: Ensure Availability for schedule/quality/competitive pricing
A20: 5. | B20: =IF('SWOT Inputs'!B33=0,"",'SWOT Inputs'!B33) -> Competition | C20: 5. | D20: Strengthen alliances with key suppliers, distributors, and partners to stabilize supply chains and ensure cost efficiencies. | E20: 5. | F20: Maintain open communication channels to address employee concerns.

Sheet Example SWOT Inputs
B2: ** EXAMPLE** INTERNAL FACTOR ANALYSIS SUMMARY (IFAS)
B3: Internal Factors | C3: Rating | D3: Utilization | E3: Comments
B4: Strengths
B5: Safety | C5: Significant Strength | D5: Always/Almost Always | E5: Zero incident in last 12 months
B6: Teamwork | C6: Strength | D6: Always/Almost Always | E6: Good communication between line and front desk. Good peer relations
B7: Interdepartmental communication | C7: Strength | D7: Often | E7: We collaborate well with other departments. Started to attend paint morning meeting and attend airframe morning meeting.
B8: Leadership | C8: Strength | D8: Often | E8: Added weekend leadership. Leadership team is very postive which is translating into the team.
B10: Internal Factors | C10: Rating | D10: Utilization | E10: Comments
B11: Weaknesses
B12: Training | C12: Significant Weakness | D12: Often | E12: Very little structure. Not enough one on one time with trainer.
B13: Invoicing Issues | C13: Weakness | D13: Sometimes | E13: Inexperienced staff creates several invoicing errors
B14: Customer Service | C14: Weakness | D14: Often | E14: Too much focus on hangar movement. Need to incorporate more customer service training on initial hire.
B19: ** EXAMPLE** EXTERNAL FACTOR ANALYSIS SUMMARY (EFAS)
B20: External Factors | C20: Likelihood | D20: Impact | E20: Comments
B21: Opportunities
B22: Bio-Bor injectors on trucks | C22: Very Likely | D22: Moderate | E22: Possibility to produce revenue by putting injectors on the trucks. Will be needed for all Falcon A-C checks.
B23: Loyalty card/program | C23: Possible | D23: Minor | E23: Repeat customers that show loyatly to Duncan will be rewarded.
B24: Customer feedback | C24: Likely | D24: Moderate | E24: create a new customer feedback form to incorporate customer dislikes and likes.
B27: Threats
B28: Oil price volatility | C28: Very Likely | D28: Moderate | E28: Oil market is unstable and changing all the time.
B29: Production shop performance | C29: Possible | D29: Moderate | E29: When production shops are slow it directly affects our shops ability to produce revenue.
B30: Employee turnover | C30: Likely | D30: Moderate | E30: A high turnover rate can lead to increased expenses due to training, overtime, quality escapes, and incident increases.

Sheet Example SWOT Matrix
A2: (Example) SWOT Matrix
D3: Strengths | F3: Weaknesses
C4: 1. | D4: ='Example SWOT Inputs'!B5 -> Safety | E4: 1. | F4: ='Example SWOT Inputs'!B12 -> Training
C5: 2. | D5: ='Example SWOT Inputs'!B6 -> Teamwork | E5: 2. | F5: ='Example SWOT Inputs'!B13 -> Invoicing Issues
C6: 3. | D6: ='Example SWOT Inputs'!B7 -> Interdepartmental communication | E6: 3. | F6: ='Example SWOT Inputs'!B14 -> Customer Service
C7: 4. | D7: ='Example SWOT Inputs'!B8 -> Leadership | E7: 4.
C8: 5. | E8: 5.
A9: Opportunities | C9: SO Strategies | E9: WO Strategies
C10: Strategies that use strengths to maximize opportunities. | E10: Strategies that minimize weaknesses by taking advantage of opportunities.
A11: 1. | B11: ='Example SWOT Inputs'!B22 -> Bio-Bor injectors on trucks | C11: 1. | D11: Knowing the requirement on bio-bor with falcons, we will look into options for a safe way to deliver the product. (S1, O1) | E11: 1. | F11: We can increase our customer service by getting customer feedback and creating a loyalty program. (W3, O2, O3)
A12: 2. | B12: ='Example SWOT Inputs'!B23 -> Loyalty card/program | C12: 2. | E12: 2.
A13: 3. | B13: ='Example SWOT Inputs'!B24 -> Customer feedback | C13: 3. | E13: 3.
A14: 4. | C14: 4. | E14: 4.
A15: 5. | C15: 5. | E15: 5.
A16: Threats | C16: ST Strategies | E16: WT Strategies
C17: Strategies that use strengths to minimize threats. | E17: Strategies that minimize weaknesses and avoid threats.
A18: 1. | B18: ='Example SWOT Inputs'!B28 -> Oil price volatility | C18: 1. | D18: Grow strong leaders to create a culutre where turnover is decreased (S4, T3) | E18: 1. | F18: With the increased rate of turnover over the last 12 months, it has brought awarness that our training is insufficient. We are going to restructure training program. (W1, T3)
A19: 2. | B19: ='Example SWOT Inputs'!B29 -> Production shop performance | C19: 2. | E19: 2.
A20: 3. | B20: ='Example SWOT Inputs'!B30 -> Employee turnover | C20: 3. | E20: 3.
A21: 4. | C21: 4. | E21: 4.
A22: 5. | C22: 5. | E22: 5.

Sheet Severity Definitions
C1: A. Catastrophic | D1: B. Major | E1: C. Moderate | F1: D. Minor | G1: E. Insignificant
B2: Aircraft / Equipment Damage | C2: Credible compromise to safety of flight | D2: Significant customer equipment damage | E2: Significant company equipment damage | F2: Minor customer equipment damage | G2: Minor company equipment damage
B3: Injury or Illness | C3: Fatality | D3: In-patient hospitalization, amputation, loss of eye | E3: Medical treatment beyond first aid, OSHA reportable incident | F3: First aid treatment | G3: No medical treatment
B4: Aircraft, Facilty or Terrorism Event | C4: Total loss of aircraft or facility | D4: NTSB accident or substantial loss of affected property | E4: NTSB incident or accident, partial loss of a facility or a credible security threat | F4: NTSB incident or minor property damage | G4: Negligible incident or damage with extremely limited effect on safety
B5: Operationsl Compliance, Performance | C5: Potential threat to Operating Certificate | D5: Regulatory/ Company policy and/or procedure deviation with a critical impact on safety | E5: Regulatory/ Company policy and/or procedure deviation with major reduction in safety margin | F5: Regulatory/ Company policy and/or procedure deviation with minor safety implication | G5: Regulatory/ Company policy and/or procedure deviation with limited safety implication
B6: Financial Impact | C6: Damage, fines or loss of revenue >$50,000 | D6: Damage, fines or loss of revenue >$10,000 - $50,000 | E6: Damage, fines or loss of revenue >$5,000 - $10,000 | F6: Damage, fines or loss of revenue >$1000 - $4,999 | G6: Damage, fines or loss of revenue <$1000
B7: Damage to the Environment | C7: Massive environmental effect | D7: Critical environmental effect | E7: Contained effect to the environment | F7: Minor environmental effect | G7: Negligible environmental effect
